simranjeet_co6_101703548/__init__.py
simranjeet_co6_101703548/topsis.py
simranjeet_co6_101703548-0.0.1.dist-info/LICENSE
simranjeet_co6_101703548-0.0.1.dist-info/METADATA
simranjeet_co6_101703548-0.0.1.dist-info/WHEEL
simranjeet_co6_101703548-0.0.1.dist-info/top_level.txt
simranjeet_co6_101703548-0.0.1.dist-info/RECORD
