Metadata-Version: 2.1
Name: simranjeet-co6-101703548
Version: 0.0.1
Summary: A small package that showcases topsis approach
Home-page: UNKNOWN
Author: Simarpreet Singh
Author-email: ssingh8_be17@thapar.edu
License: UNKNOWN
Platform: UNKNOWN
Classifier: Programming Language :: Python :: 3
Classifier: License :: OSI Approved :: MIT License
Classifier: Operating System :: OS Independent
Requires-Python: >=3.6
